MANIFEST.in
README.md
setup.py
copr/__info__.py
copr/__init__.py
copr/copr.py
copr/scheme.json
copr.py.egg-info/PKG-INFO
copr.py.egg-info/SOURCES.txt
copr.py.egg-info/dependency_links.txt
copr.py.egg-info/requires.txt
copr.py.egg-info/top_level.txt
tests/test_aspect.py
tests/test_asset.py
tests/test_general.py
tests/test_literature.py
tests/test_representation.py